migrate/__init__.py
migrate/_runner.py
migrate/cli.py
migrations-0.1.1.dist-info/DESCRIPTION.rst
migrations-0.1.1.dist-info/METADATA
migrations-0.1.1.dist-info/RECORD
migrations-0.1.1.dist-info/WHEEL
migrations-0.1.1.dist-info/entry_points.txt
migrations-0.1.1.dist-info/metadata.json
migrations-0.1.1.dist-info/top_level.txt
