Metadata-Version: 1.1
Name: migrations
Version: 0.1.1
Summary: Yet another Python migration tool
Home-page: https://github.com/and800/migrations
Author: Andriy Maletsky
Author-email: andriy.maletsky@gmail.com
License: MIT
Keywords: migration
Platform: UNKNOWN
Classifier: Development Status :: 4 - Beta
Classifier: Environment :: Console
Classifier: Intended Audience :: Developers
Classifier: License :: OSI Approved :: MIT License
Classifier: Programming Language :: Python :: 3.5
Classifier: Topic :: Software Development :: Version Control
